onelogger/__init__.py
onelogger/logger.py
onelogger/oneenv_decorator.py
onelogger-0.1.3.dist-info/LICENSE
onelogger-0.1.3.dist-info/METADATA
onelogger-0.1.3.dist-info/WHEEL
onelogger-0.1.3.dist-info/top_level.txt
onelogger-0.1.3.dist-info/RECORD
