Metadata-Version: 2.2
Name: onelogger
Version: 0.1.3
Summary: Oneenv-based settings management and fast logging library
Requires-Python: >=3.11
License-File: LICENSE
Requires-Dist: oneenv>=0.1.5
Requires-Dist: picologging>=0.1.5; python_version < "3.13"
Provides-Extra: dev
Requires-Dist: pytest>=7.4.0; extra == "dev"
Requires-Dist: pytest-cov>=4.1.0; extra == "dev"
